{
  "facility_code": "31801137",
  "institution": "LINFIELD COLLEGE (MCMINNVILLE CAMPUS)",
  "city": "MCMINNVILLE",
  "state": "OR",
  "zip": "97128",
  "country": "USA",
  "type": "Private",
  "cross": 209065,
  "ope": "00319800",
  "bah": 1533,
  "poe": true,
  "yr": true,
  "gibill": 45,
  "student_veteran": null,
  "student_veteran_link": null,
  "vetsuccess_name": null,
  "vetsuccess_email": null,
  "eight_keys": null,
  "correspondence": null,
  "flight": null,
  "grad_rate": 67.2,
  "grad_rate_rank": 375,
  "default_rate": 4.7,
  "avg_stu_loan_debt": 25000,
  "avg_stu_loan_debt_rank": 1712,
  "indicator_group": 1,
  "salary": null,
  "calendar": "nontraditional",
  "tuition_in_state": 36310,
  "tuition_out_of_state": 36310
}