{
  "facility_code": "219C5110",
  "institution": "JOSE MARIA VARGAS UNIVERSITY",
  "city": "PEMBROKE PINES",
  "state": "FL",
  "zip": "33025",
  "country": "USA",
  "type": "For Profit",
  "cross": 461281,
  "ope": "04162000",
  "bah": 2073,
  "poe": true,
  "yr": null,
  "gibill": null,
  "student_veteran": null,
  "student_veteran_link": null,
  "vetsuccess_name": null,
  "vetsuccess_email": null,
  "eight_keys": null,
  "correspondence": null,
  "flight": null,
  "grad_rate": null,
  "grad_rate_rank": null,
  "default_rate": null,
  "avg_stu_loan_debt": 2689,
  "avg_stu_loan_debt_rank": 13,
  "indicator_group": 3,
  "salary": null,
  "calendar": "semesters",
  "tuition_in_state": 8360,
  "tuition_out_of_state": 8360
}