{
  "facility_code": "31601025",
  "institution": "ST. LOUIS CHRISTIAN COLLEGE",
  "city": "FLORISSANT",
  "state": "MO",
  "zip": "63033",
  "country": "USA",
  "type": "Private",
  "cross": 179256,
  "ope": "01258000",
  "bah": 1284,
  "poe": null,
  "yr": true,
  "gibill": 7,
  "student_veteran": null,
  "student_veteran_link": null,
  "vetsuccess_name": null,
  "vetsuccess_email": null,
  "eight_keys": null,
  "correspondence": null,
  "flight": null,
  "grad_rate": 39.1,
  "grad_rate_rank": 1281,
  "default_rate": 12.6,
  "avg_stu_loan_debt": 12250,
  "avg_stu_loan_debt_rank": 293,
  "indicator_group": 1,
  "salary": null,
  "calendar": "semesters",
  "tuition_in_state": 8215,
  "tuition_out_of_state": 8215
}