{
  "facility_code": "28399732",
  "institution": "LONG ISLAND BEAUTY SCHOOL INC",
  "city": "HAUPPAUGE",
  "state": "NY",
  "zip": "11788",
  "country": "USA",
  "type": "For Profit",
  "cross": 383297,
  "ope": "00738700",
  "bah": 2697,
  "poe": null,
  "yr": null,
  "gibill": 2,
  "student_veteran": null,
  "student_veteran_link": null,
  "vetsuccess_name": null,
  "vetsuccess_email": null,
  "eight_keys": null,
  "correspondence": null,
  "flight": null,
  "grad_rate": 71.8,
  "grad_rate_rank": 1085,
  "default_rate": 9.1,
  "avg_stu_loan_debt": 6481,
  "avg_stu_loan_debt_rank": 534,
  "indicator_group": 5,
  "salary": null,
  "calendar": "nontraditional",
  "tuition_in_state": null,
  "tuition_out_of_state": null
}