{
  "facility_code": "15017346",
  "institution": "WOODROW WILSON REHAB CTR-PRG ASST DIRECTOR",
  "city": "FISHERSVILLE",
  "state": "VA",
  "zip": "22939",
  "country": "USA",
  "type": "Public",
  "cross": 234359,
  "ope": "02197600",
  "bah": 1200,
  "poe": true,
  "yr": null,
  "gibill": 1,
  "student_veteran": null,
  "student_veteran_link": null,
  "vetsuccess_name": null,
  "vetsuccess_email": null,
  "eight_keys": null,
  "correspondence": null,
  "flight": null,
  "grad_rate": 76.0,
  "grad_rate_rank": 865,
  "default_rate": null,
  "avg_stu_loan_debt": null,
  "avg_stu_loan_debt_rank": null,
  "indicator_group": 5,
  "salary": null,
  "calendar": "nontraditional",
  "tuition_in_state": null,
  "tuition_out_of_state": null
}