{
  "facility_code": "11800918",
  "institution": "LOUISIANA STATE UNIVERSITY SHREVEPORT",
  "city": "SHREVEPORT",
  "state": "LA",
  "zip": "71115",
  "country": "USA",
  "type": "Public",
  "cross": 159416,
  "ope": "00201300",
  "bah": 1428,
  "poe": true,
  "yr": true,
  "gibill": 266,
  "student_veteran": null,
  "student_veteran_link": null,
  "vetsuccess_name": null,
  "vetsuccess_email": null,
  "eight_keys": null,
  "correspondence": null,
  "flight": null,
  "grad_rate": 26.9,
  "grad_rate_rank": 1596,
  "default_rate": 12.2,
  "avg_stu_loan_debt": 13545,
  "avg_stu_loan_debt_rank": 402,
  "indicator_group": 1,
  "salary": null,
  "calendar": "semesters",
  "tuition_in_state": 5606,
  "tuition_out_of_state": 5606
}