{
  "facility_code": "15526225",
  "institution": "LEBANON TECHNOLOGY AND CAREER CENTER",
  "city": "LEBANON",
  "state": "MO",
  "zip": "65536",
  "country": "USA",
  "type": "Public",
  "cross": 374112,
  "ope": "03042400",
  "bah": 1053,
  "poe": true,
  "yr": null,
  "gibill": 2,
  "student_veteran": null,
  "student_veteran_link": null,
  "vetsuccess_name": null,
  "vetsuccess_email": null,
  "eight_keys": null,
  "correspondence": null,
  "flight": null,
  "grad_rate": 80.0,
  "grad_rate_rank": 635,
  "default_rate": 12.5,
  "avg_stu_loan_debt": 12050,
  "avg_stu_loan_debt_rank": 1781,
  "indicator_group": 5,
  "salary": null,
  "calendar": "nontraditional",
  "tuition_in_state": null,
  "tuition_out_of_state": null
}