{
  "facility_code": "25801409",
  "institution": "BENNETT CAREER INSTITUTE",
  "city": "WASHINGTON",
  "state": "DC",
  "zip": "20017",
  "country": "USA",
  "type": "For Profit",
  "cross": 439473,
  "ope": "03409600",
  "bah": 2175,
  "poe": null,
  "yr": null,
  "gibill": 18,
  "student_veteran": null,
  "student_veteran_link": null,
  "vetsuccess_name": null,
  "vetsuccess_email": null,
  "eight_keys": null,
  "correspondence": null,
  "flight": null,
  "grad_rate": 66.1,
  "grad_rate_rank": 1379,
  "default_rate": 39.7,
  "avg_stu_loan_debt": 3847,
  "avg_stu_loan_debt_rank": 143,
  "indicator_group": 5,
  "salary": null,
  "calendar": "nontraditional",
  "tuition_in_state": null,
  "tuition_out_of_state": null
}