{
  "facility_code": "31043213",
  "institution": "IIT-CHICAGO-KENT COLLEGE OF LAW",
  "city": "CHICAGO",
  "state": "IL",
  "zip": "60661",
  "country": "USA",
  "type": "Private",
  "cross": 145725,
  "ope": "00169100",
  "bah": 1977,
  "poe": null,
  "yr": true,
  "gibill": 16,
  "student_veteran": null,
  "student_veteran_link": null,
  "vetsuccess_name": null,
  "vetsuccess_email": null,
  "eight_keys": null,
  "correspondence": null,
  "flight": null,
  "grad_rate": 68.3,
  "grad_rate_rank": 342,
  "default_rate": 3.4,
  "avg_stu_loan_debt": 23474,
  "avg_stu_loan_debt_rank": 1572,
  "indicator_group": 1,
  "salary": null,
  "calendar": "semesters",
  "tuition_in_state": 40117,
  "tuition_out_of_state": 40117
}