{
  "facility_code": "31904127",
  "institution": "GRACE UNIVERSITY",
  "city": "OMAHA",
  "state": "NE",
  "zip": "68108",
  "country": "USA",
  "type": "Private",
  "cross": 181093,
  "ope": "00254700",
  "bah": 1194,
  "poe": true,
  "yr": true,
  "gibill": 28,
  "student_veteran": null,
  "student_veteran_link": null,
  "vetsuccess_name": null,
  "vetsuccess_email": null,
  "eight_keys": null,
  "correspondence": null,
  "flight": null,
  "grad_rate": 41.3,
  "grad_rate_rank": 1201,
  "default_rate": 5.5,
  "avg_stu_loan_debt": 14500,
  "avg_stu_loan_debt_rank": 484,
  "indicator_group": 1,
  "salary": null,
  "calendar": "semesters",
  "tuition_in_state": 18256,
  "tuition_out_of_state": 18256
}