{
  "facility_code": "31901121",
  "institution": "CURRY COLLEGE",
  "city": "MILTON",
  "state": "MA",
  "zip": "02186",
  "country": "USA",
  "type": "Private",
  "cross": 165529,
  "ope": "00214300",
  "bah": 2817,
  "poe": null,
  "yr": true,
  "gibill": 125,
  "student_veteran": null,
  "student_veteran_link": null,
  "vetsuccess_name": null,
  "vetsuccess_email": null,
  "eight_keys": null,
  "correspondence": null,
  "flight": null,
  "grad_rate": 42.7,
  "grad_rate_rank": 1153,
  "default_rate": 9.4,
  "avg_stu_loan_debt": 23250,
  "avg_stu_loan_debt_rank": 1549,
  "indicator_group": 1,
  "salary": null,
  "calendar": "semesters",
  "tuition_in_state": 34715,
  "tuition_out_of_state": 34715
}