{
  "facility_code": "319A3138",
  "institution": "KEYSTONE COLLEGE",
  "city": "LAPLUME",
  "state": "PA",
  "zip": "18440",
  "country": "USA",
  "type": "Private",
  "cross": 213303,
  "ope": "00328000",
  "bah": 1230,
  "poe": null,
  "yr": true,
  "gibill": 61,
  "student_veteran": true,
  "student_veteran_link": null,
  "vetsuccess_name": null,
  "vetsuccess_email": null,
  "eight_keys": null,
  "correspondence": null,
  "flight": null,
  "grad_rate": 44.7,
  "grad_rate_rank": 1076,
  "default_rate": 12.0,
  "avg_stu_loan_debt": 18750,
  "avg_stu_loan_debt_rank": 1007,
  "indicator_group": 1,
  "salary": null,
  "calendar": "semesters",
  "tuition_in_state": 21300,
  "tuition_out_of_state": 21300
}