{
  "facility_code": "24911415",
  "institution": "VATTEROTT COLLEGE DES MOINES",
  "city": "DES MOINES",
  "state": "IA",
  "zip": "50321",
  "country": "USA",
  "type": "For Profit",
  "cross": 373058,
  "ope": "02609200",
  "bah": 1359,
  "poe": true,
  "yr": true,
  "gibill": 28,
  "student_veteran": null,
  "student_veteran_link": null,
  "vetsuccess_name": null,
  "vetsuccess_email": null,
  "eight_keys": null,
  "correspondence": null,
  "flight": null,
  "grad_rate": 59.6,
  "grad_rate_rank": 298,
  "default_rate": 21.6,
  "avg_stu_loan_debt": 19533,
  "avg_stu_loan_debt_rank": 713,
  "indicator_group": 3,
  "salary": null,
  "calendar": "nontraditional",
  "tuition_in_state": 12839,
  "tuition_out_of_state": 12839
}