{
  "facility_code": "24926148",
  "institution": "VALLEY COLLEGE",
  "city": "MARTINSBURG",
  "state": "WV",
  "zip": "25404",
  "country": "USA",
  "type": "For Profit",
  "cross": 377661,
  "ope": "02609400",
  "bah": 1164,
  "poe": true,
  "yr": null,
  "gibill": 11,
  "student_veteran": null,
  "student_veteran_link": null,
  "vetsuccess_name": null,
  "vetsuccess_email": null,
  "eight_keys": null,
  "correspondence": null,
  "flight": null,
  "grad_rate": 66.7,
  "grad_rate_rank": 216,
  "default_rate": 20.2,
  "avg_stu_loan_debt": 8601,
  "avg_stu_loan_debt_rank": 270,
  "indicator_group": 3,
  "salary": null,
  "calendar": "nontraditional",
  "tuition_in_state": null,
  "tuition_out_of_state": null
}