{
  "facility_code": "24931614",
  "institution": "KAPLAN COLLEGE - SE INDIANAPOLIS",
  "city": "INDIANAPOLIS",
  "state": "IN",
  "zip": "46227",
  "country": "USA",
  "type": "For Profit",
  "cross": 458283,
  "ope": "00977703",
  "bah": 1176,
  "poe": true,
  "yr": true,
  "gibill": 40,
  "student_veteran": null,
  "student_veteran_link": null,
  "vetsuccess_name": null,
  "vetsuccess_email": null,
  "eight_keys": null,
  "correspondence": null,
  "flight": null,
  "grad_rate": 71.5,
  "grad_rate_rank": 152,
  "default_rate": 21.3,
  "avg_stu_loan_debt": 9500,
  "avg_stu_loan_debt_rank": 361,
  "indicator_group": 3,
  "salary": null,
  "calendar": "nontraditional",
  "tuition_in_state": null,
  "tuition_out_of_state": null
}