{
  "facility_code": "249C4410",
  "institution": "AMERICAN MEDICAL ACADEMY",
  "city": "MIAMI",
  "state": "FL",
  "zip": "33186",
  "country": "USA",
  "type": "For Profit",
  "cross": 475714,
  "ope": "04192100",
  "bah": 2073,
  "poe": true,
  "yr": null,
  "gibill": 35,
  "student_veteran": null,
  "student_veteran_link": null,
  "vetsuccess_name": null,
  "vetsuccess_email": null,
  "eight_keys": true,
  "correspondence": null,
  "flight": null,
  "grad_rate": 81.6,
  "grad_rate_rank": 53,
  "default_rate": null,
  "avg_stu_loan_debt": null,
  "avg_stu_loan_debt_rank": null,
  "indicator_group": 3,
  "salary": null,
  "calendar": "nontraditional",
  "tuition_in_state": null,
  "tuition_out_of_state": null
}