{
  "facility_code": "14921166",
  "institution": "COLLEGE OF THE MARSHALL ISLANDS",
  "city": "MAJURO",
  "state": "MH",
  "zip": "96960",
  "country": "USA",
  "type": "Public",
  "cross": 376695,
  "ope": "03022400",
  "bah": 800,
  "poe": null,
  "yr": null,
  "gibill": 1,
  "student_veteran": null,
  "student_veteran_link": null,
  "vetsuccess_name": null,
  "vetsuccess_email": null,
  "eight_keys": null,
  "correspondence": null,
  "flight": null,
  "grad_rate": 9.9,
  "grad_rate_rank": 1295,
  "default_rate": null,
  "avg_stu_loan_debt": null,
  "avg_stu_loan_debt_rank": null,
  "indicator_group": 2,
  "salary": null,
  "calendar": "semesters",
  "tuition_in_state": 4905,
  "tuition_out_of_state": 4905
}