{
  "facility_code": "14921404",
  "institution": "COLLEGE OF THE OUACHITAS",
  "city": "MALVERN",
  "state": "AR",
  "zip": "72104",
  "country": "USA",
  "type": "Public",
  "cross": 107521,
  "ope": "00997600",
  "bah": 978,
  "poe": true,
  "yr": null,
  "gibill": 33,
  "student_veteran": null,
  "student_veteran_link": null,
  "vetsuccess_name": null,
  "vetsuccess_email": null,
  "eight_keys": null,
  "correspondence": null,
  "flight": null,
  "grad_rate": 29.3,
  "grad_rate_rank": 547,
  "default_rate": 26.3,
  "avg_stu_loan_debt": 4850,
  "avg_stu_loan_debt_rank": 87,
  "indicator_group": 3,
  "salary": null,
  "calendar": "semesters",
  "tuition_in_state": 3367,
  "tuition_out_of_state": 5917
}