{
  "facility_code": "14924149",
  "institution": "WAUKESHA COUNTY TECHNICAL COLLEGE-WCTC",
  "city": "PEWAUKEE",
  "state": "WI",
  "zip": "53072",
  "country": "USA",
  "type": "Public",
  "cross": 240125,
  "ope": "00529400",
  "bah": 1692,
  "poe": true,
  "yr": null,
  "gibill": 265,
  "student_veteran": null,
  "student_veteran_link": null,
  "vetsuccess_name": null,
  "vetsuccess_email": null,
  "eight_keys": true,
  "correspondence": null,
  "flight": null,
  "grad_rate": 31.5,
  "grad_rate_rank": 529,
  "default_rate": 15.9,
  "avg_stu_loan_debt": 9243,
  "avg_stu_loan_debt_rank": 327,
  "indicator_group": 3,
  "salary": null,
  "calendar": "semesters",
  "tuition_in_state": 3885,
  "tuition_out_of_state": 5718
}