{
  "facility_code": "14939413",
  "institution": "PRAIRIE STATE COLLEGE",
  "city": "CHICAGO HEIGHTS",
  "state": "IL",
  "zip": "60411",
  "country": "USA",
  "type": "Public",
  "cross": 148007,
  "ope": "00164000",
  "bah": 1977,
  "poe": true,
  "yr": null,
  "gibill": 254,
  "student_veteran": true,
  "student_veteran_link": "http://prairiestate.edu/vetsclub/index.html",
  "vetsuccess_name": null,
  "vetsuccess_email": null,
  "eight_keys": null,
  "correspondence": null,
  "flight": null,
  "grad_rate": 11.9,
  "grad_rate_rank": 706,
  "default_rate": 18.4,
  "avg_stu_loan_debt": 6500,
  "avg_stu_loan_debt_rank": 171,
  "indicator_group": 3,
  "salary": null,
  "calendar": "semesters",
  "tuition_in_state": 6984,
  "tuition_out_of_state": 8304
}