{
  "facility_code": "14940436",
  "institution": "SEMINOLE STATE COLLEGE",
  "city": "SEMINOLE",
  "state": "OK",
  "zip": "74868",
  "country": "USA",
  "type": "Public",
  "cross": 207740,
  "ope": "00317800",
  "bah": 1053,
  "poe": true,
  "yr": null,
  "gibill": 78,
  "student_veteran": null,
  "student_veteran_link": null,
  "vetsuccess_name": null,
  "vetsuccess_email": null,
  "eight_keys": true,
  "correspondence": null,
  "flight": null,
  "grad_rate": 20.1,
  "grad_rate_rank": 933,
  "default_rate": 32.3,
  "avg_stu_loan_debt": 7920,
  "avg_stu_loan_debt_rank": 545,
  "indicator_group": 2,
  "salary": null,
  "calendar": "semesters",
  "tuition_in_state": 3425,
  "tuition_out_of_state": 8075
}