{
  "facility_code": "14997443",
  "institution": "RANGER COLLEGE",
  "city": "RANGER",
  "state": "TX",
  "zip": "76470",
  "country": "USA",
  "type": "Public",
  "cross": 227687,
  "ope": "00360300",
  "bah": 1071,
  "poe": null,
  "yr": null,
  "gibill": 29,
  "student_veteran": null,
  "student_veteran_link": null,
  "vetsuccess_name": null,
  "vetsuccess_email": null,
  "eight_keys": null,
  "correspondence": null,
  "flight": null,
  "grad_rate": 21.4,
  "grad_rate_rank": 631,
  "default_rate": 24.3,
  "avg_stu_loan_debt": 4486,
  "avg_stu_loan_debt_rank": 63,
  "indicator_group": 3,
  "salary": null,
  "calendar": "semesters",
  "tuition_in_state": 3870,
  "tuition_out_of_state": 4830
}